{"vars":{"cc_joinGame":"value_undefined","cc_hitThem":"value_undefined","cc_fire":"value_undefined","cc_eggOrgUpdate":"value_undefined","callApi":"value_undefined","firebaseUser":"value_undefined","MapData":"value_undefined","CommCodeStart":"0","CONTROLKEYS":"KN","_chat":"i","addChat":"BP","player_":"Gp","meshesToLoad":"\"egg\",\"gun_eggk47\",\"gun_csg1\",\"gun_cluck9mm\",\"gun_dozenGauge\",\"gun_rpegg\",\"gun_smg\",\"gun_m24\",\"gun_aug\",\"melee\",\"munitions\"","cc_hitMeHardBoiled":"ez","cc_bootPlayer":"k","spectate":"YN","cc_requestGameOptions":"_","cc_gameAction":"j","grenadeCapacity":"Cu","uniqueId":"fz","_deathFunction":"OP","CULL":"Xw","hp":"mu","_connectFail":"QD","_update":"Ju","randomGen":"_p","Grenade":"SR","BabylonVersion":"7.21.1","_playerThing":"HR","cc_collectItem":"Rz","CommCode":"{u:100,I:101,S:102,t:103,G:104,v:105,k:106,P:107,U:108,T:109,H:110,V:111,W:112,C:113,D:114,M:115,$:116,j:117,_:118,F:119,K:120,J:121,N:122,O:123,i:124,pz:125,uz:126,Iz:127,Qz:128,Sz:129,Rz:130,hz:131,tz:132,Gz:133,vz:134,kz:135,Pz:136,Uz:137,Tz:138,az:139,bz:140,Yz:141,xz:142,mz:143,qz:144,cz:145,Az:146,Zz:147,Ez:148,Xz:149,dz:150,Vz:151,Wz:152,Cz:153,Dz:154,Mz:155,$z:156,jz:157,ez:158,Fz:159,Kz:160,Jz:161}","cc_ping":"v","cc_metaGameState":"Cz","cc_removePlayer":"N","cc_chat":"vz","cc_reload":"mz","cc_melee":"i","cc_updateBalance":"xz","gunContainer":"II","renderingGroupId":"pp","sourceMesh":"Ip","name_":"Lp","spectator":"wN","actor":"vp","respawnTime":"EN","commOut":"Rh","CloseCode":"{gameNotFound:0,gameFull:0,badName:0,mainMenu:0,gameIdleExceeded:0,corruptedLoginData0:0,corruptedLoginData1:0,corruptedLoginData2:0,corruptedLoginData3:0,corruptedLoginData4:0,corruptedLoginData5:0,gameMaxPlayersExceeded:0,gameDestroyUser:0,joinGameOutOfOrder:0,gameShuttingDown:0,readyBeforeReady:0,booted:0,gameErrorOnUserSocket:0,uuidNotFound:0,sessionNotFound:0,clusterFullCpu:0,clusterFullMem:0,noClustersAvailable:0,locked:0}","CloseCodeStart":"4e3","cloneMesh":"lR","firebaseConfig":"t","teamUI":"ck","TransformNode":"Jc","RotationYawPitchRoll":"Lz","Matrix":"Hc","MeshBuilder":"cS","CreateLines":"Ty","Viewport":"gd","VertexBuffer":"eu","rootUrl":"u","meshIdx":"c","loadMeshes":"XR","meshPath":"m","meshOnSuccess":"f","SceneLoader":"qS","VertexData":"Mu","enterSpectatorModeBlocked":"ZI","Vector3":"Lc","fov":"iz","weapon":"Yp","weaponIdx":"Mp","grenadeCount":"Wu","dz":"tp","rounds":"ep","accuracyMin":"Wp","accuracyMax":"Cp","accuracyLoss":"Dp","cc_syncMe":"Dz","cc_pause":"M","cc_eventModifier":"Iz","cc_gameOptions":"$","cc_changeCharacter":"D","cc_musicInfo":"jz","cc_challengeCompleted":"Kz","cc_throwGrenade":"pz","cc_switchTeam":"C","cc_endShellStreak":"az","cc_die":"Uz","cc_socketReady":"K","cc_gameJoined":"F","cc_clientReady":"Zz","cc_reportPlayer":"H","cc_spawnItem":"t","cc_beginShellStreak":"Tz","cc_requestRespawn":"Ez","cc_respawnDenied":"cz","cc_syncThem":"kz","cc_respawn":"qz","cc_addPlayer":"J","cc_keepAlive":"$z","cc_explode":"Mz","GrenadeActor":"DO","capacity":"nz","storeMax":"Hp","_filterFunction":"eN","ws":"Pk","mesh":"mesh","OBJECTSVAR":"tw","RAYS":"_R","skybox":"l","isBadWord":"eN","nameTexture":"oI","globalScene":"Zk","spectateMode":"jN","_insideFilterFunction":"e","signedInFunc":"FP","grenadeThrowPower":"aI","GetBabylon":"uc","itemRenderer":"qO","playerInfo":"kh","uniqueId_":"Jp","playing":"cp","Color3":"wc","pitch":"jp","coords":"hu","renderList":"zp","MYPLAYER":"$k","mapData":"iI","z":"Ep","SCENE":"eI","CAMERA":"iw","stateBuffer":"_u","SETTINGS":"Fw","yaw":"$p","x":"Ap","bodyMesh":"Lu","WEAPONS":"kh","GAMEMAP":"tI","CONTROLKEYSENUM":"OR","USERDATA":"kh","ERRORARRAY":"th","render":"render","playerData":"d","minMaps":"NR","teamColors":"YT","PLAYERS":"rI","rayCollidesWithMap":"bp","y":"Zp"},"checksum":"aa0f47bac40654043fdcd3fd3c87a783dc3d3c1fc4c23b5db180ad6a401412b2","client_name":"all","time":1782874888615,"CommCodes":null}