{"vars": {"PLAYERS": "jb", "playing": "Mp", "mesh": "D", "yaw": "Ep", "pitch": "Op", "SCENE": "Hb", "bodyMesh": "tW", "CONTROLKEYSENUM": "Ex", "USERDATA": "Tc", "CONTROLKEYS": "Lb", "hp": "Fp", "_connectFail": "oD", "render": "render", "_filterFunction": "Ux", "_insideFilterFunction": "e", "_update": "aW", "skybox": "l", "isBadWord": "Ux", "playerData": "d", "uniqueId_": "Jp", "name_": "xp", "actor": "i", "nameTexture": "Kb", "MYPLAYER": "pO"}, "checksum": "0ea79e6105e7ae9773317ef9fd487c2a7f2a2ad22c8462da15e7b26456364775"}