{"vars":{"mesh":"Xb","CONTROLKEYS":"controlKeys","_filterFunction":"isBadWord","hp":"Oz","_connectFail":"handleCloseCode","_update":"Uz","skybox":"l","isBadWord":"isBadWord","SCENE":"gameScene","MYPLAYER":"me","name_":"Bb","actor":"wb","_insideFilterFunction":"e","nameTexture":"nameTexture","uniqueId_":"yb","yaw":"pb","pitch":"Jb","bodyMesh":"Bz","CONTROLKEYSENUM":"CONTROL","USERDATA":"G","render":"render","playerData":"d","PLAYERS":"players"},"checksum":"93f8da3c597518156b55852c290e31188950d3e49bef2d5782be77e478adb8c7","client_name":"shellfarm","time":1743737530187}