{"vars":{"mesh":"Xb","CONTROLKEYS":"controlKeys","_filterFunction":"isBadWord","hp":"Oz","_connectFail":"handleCloseCode","_update":"Uz","skybox":"l","isBadWord":"isBadWord","SCENE":"gameScene","MYPLAYER":"me","name_":"Bb","actor":"wb","_insideFilterFunction":"e","nameTexture":"nameTexture","uniqueId_":"yb","yaw":"pb","pitch":"Jb","bodyMesh":"Bz","CONTROLKEYSENUM":"CONTROL","USERDATA":"G","render":"render","playerData":"d","PLAYERS":"players"},"checksum":"cf4973466789423fbef7e592dca90845b88a62f8ec805b12795e131beb03e3d0","client_name":"shellfarm","time":1743736253106}