{"vars": {"PLAYERS": "Nn", "playing": "WY", "mesh": "k", "yaw": "lY", "pitch": "hY", "x": "xY", "y": "$Y", "z": "jY", "SCENE": "An", "CULL": "Ee", "renderList": "U", "rayCollidesWithMap": "DY", "bodyMesh": "Pk", "WEAPONS": "A", "OBJECTSVAR": "G", "GAMEMAP": "Mn", "CAMERA": "W", "RAYS": "Lt", "SETTINGS": "ye", "CONTROLKEYSENUM": "si", "USERDATA": "A", "CONTROLKEYS": "yn", "SERVERCODES": "n", "hp": "oY", "stateBuffer": "Fk", "_connectFail": "Br", "ERRORARRAY": "t", "render": "render", "_chat": "i", "_filterFunction": "Ai", "_insideFilterFunction": "e", "_deathFunction": "os", "_playerThing": "ci", "_update": "Wk", "randomGen": "qY", "skybox": "o", "mapData": "Pn", "isBadWord": "Ai", "playerData": "y", "uniqueId_": "RY", "name_": "dY", "spectator": "qi", "spectateMode": "gn", "actor": "YY", "nameTexture": "Rn", "addChat": "us", "player_": "BY", "firebaseUser": "Oe", "respawnTime": "zi", "commOut": "S"}, "checksum": "5cc2638fda1dc68f7b39d8c84b08026e0594cc1cbe0a6a6110349559e6f6dc04"}