{"vars": {"PLAYERS": "players", "playing": "value_undefined", "mesh": "value_undefined", "yaw": "value_undefined", "pitch": "value_undefined", "x": "value_undefined", "y": "value_undefined", "z": "value_undefined", "SCENE": "gameScene", "CULL": "value_undefined", "renderList": "renderList", "rayCollidesWithMap": "value_undefined", "bodyMesh": "value_undefined", "WEAPONS": "value_undefined", "OBJECTSVAR": "value_undefined", "GAMEMAP": "value_undefined", "CAMERA": "camera", "RAYS": "Collider", "SETTINGS": "value_undefined", "CONTROLKEYSENUM": "value_undefined", "USERDATA": "value_undefined", "CONTROLKEYS": "value_undefined", "SERVERCODES": "CommCode", "hp": "value_undefined", "stateBuffer": "value_undefined", "_connectFail": "value_undefined", "ERRORARRAY": "CloseCode", "render": "render", "_chat": "value_undefined", "_filterFunction": "value_undefined", "_insideFilterFunction": "value_undefined", "_deathFunction": "value_undefined", "_playerThing": "value_undefined", "_update": "value_undefined", "randomGen": "randomGen_"}, "checksum": "a086bffb6fd3de2776c1c55ca7a70e466fab05d5bd5794e2d2715eae1916926c"}